aoikwinprockill/aoikwpk.py
aoikwinprockill/__init__.py
aoikwinprockill/__main__.py
AoikWinProcKill-0.1.0.dist-info/DESCRIPTION.rst
AoikWinProcKill-0.1.0.dist-info/entry_points.txt
AoikWinProcKill-0.1.0.dist-info/METADATA
AoikWinProcKill-0.1.0.dist-info/metadata.json
AoikWinProcKill-0.1.0.dist-info/RECORD
AoikWinProcKill-0.1.0.dist-info/top_level.txt
AoikWinProcKill-0.1.0.dist-info/WHEEL
