Metadata-Version: 2.0
Name: AoikWinProcKill
Version: 0.1.0
Summary: Kill Windows processes by matching their full command line with regular expression.
Home-page: https://github.com/AoiKuiyuyou/AoikWinProcKill
Author: Aoi.Kuiyuyou
Author-email: aoi.kuiyuyou@google.com
License: MIT
Keywords: Kill Windows process command line regular expression
Platform: UNKNOWN
Classifier: Development Status :: 3 - Alpha
Classifier: Environment :: Console
Classifier: Intended Audience :: End Users/Desktop
Classifier: Intended Audience :: System Administrators
Classifier: License :: OSI Approved :: MIT License
Classifier: Operating System :: Microsoft :: Windows
Classifier: Programming Language :: Python :: 2
Classifier: Programming Language :: Python :: 2.7
Classifier: Programming Language :: Python :: 3
Classifier: Programming Language :: Python :: 3.2
Classifier: Programming Language :: Python :: 3.3
Classifier: Programming Language :: Python :: 3.4
